  0           RESUME                   0

  1           LOAD_CONST               0 ('Shared configuration for RAG pipeline (Tasks 4–10).')
              STORE_NAME               0 (__doc__)

  3           LOAD_CONST               1 (0)
              LOAD_CONST               2 (None)
              IMPORT_NAME              1 (os)
              STORE_NAME               1 (os)

  4           LOAD_CONST               1 (0)
              LOAD_CONST               3 (('Path',))
              IMPORT_NAME              2 (pathlib)
              IMPORT_FROM              3 (Path)
              STORE_NAME               3 (Path)
              POP_TOP

  6           LOAD_CONST               1 (0)
              LOAD_CONST               4 (('load_dotenv',))
              IMPORT_NAME              4 (dotenv)
              IMPORT_FROM              5 (load_dotenv)
              STORE_NAME               5 (load_dotenv)
              POP_TOP

  8           LOAD_NAME                5 (load_dotenv)
              PUSH_NULL
              CALL                     0
              POP_TOP

 10           LOAD_NAME                3 (Path)
              PUSH_NULL
              LOAD_NAME                6 (__file__)
              CALL                     1
              LOAD_ATTR               14 (parent)
              LOAD_ATTR               14 (parent)
              STORE_NAME               8 (PROJECT_ROOT)

 11           LOAD_NAME                8 (PROJECT_ROOT)
              LOAD_CONST               5 ('data')
              BINARY_OP               11 (/)
              LOAD_CONST               6 ('standardized')
              BINARY_OP               11 (/)
              STORE_NAME               9 (STANDARDIZED_DIR)

 12           LOAD_NAME                8 (PROJECT_ROOT)
              LOAD_CONST               5 ('data')
              BINARY_OP               11 (/)
              LOAD_CONST               7 ('processed')
              BINARY_OP               11 (/)
              STORE_NAME              10 (PROCESSED_DIR)

 16           LOAD_CONST               8 (800)
              STORE_NAME              11 (CHUNK_SIZE)

 17           LOAD_CONST               9 (120)
              STORE_NAME              12 (CHUNK_OVERLAP)

 18           LOAD_CONST              10 ('recursive')
              STORE_NAME              13 (CHUNKING_METHOD)

 20           BUILD_LIST               0
              LOAD_CONST              11 (('\n\n**Điều', '\n\n**Chương', '\n\n# ', '\n\n## ', '\n\n', '\n', '. ', ' ', ''))
              LIST_EXTEND              1
              STORE_NAME              14 (CHUNK_SEPARATORS)

 33           LOAD_CONST              12 ('BAAI/bge-m3')
              STORE_NAME              15 (EMBEDDING_MODEL)

 34           LOAD_CONST              13 (1024)
              STORE_NAME              16 (EMBEDDING_DIM)

 36           LOAD_CONST              14 ('weaviate')
              STORE_NAME              17 (VECTOR_STORE)

 37           LOAD_CONST              15 ('DrugLawDocs')
              STORE_NAME              18 (WEAVIATE_COLLECTION)

 38           LOAD_NAME                1 (os)
              LOAD_ATTR               38 (getenv)
              PUSH_NULL
              LOAD_CONST              16 ('WEAVIATE_URL')
              LOAD_CONST              17 ('')
              CALL                     2
              STORE_NAME              20 (WEAVIATE_URL)

 39           LOAD_NAME                1 (os)
              LOAD_ATTR               38 (getenv)
              PUSH_NULL
              LOAD_CONST              18 ('WEAVIATE_API_KEY')
              LOAD_CONST              17 ('')
              CALL                     2
              STORE_NAME              21 (WEAVIATE_API_KEY)

 41           LOAD_NAME               10 (PROCESSED_DIR)
              LOAD_CONST              19 ('chunks.json')
              BINARY_OP               11 (/)
              STORE_NAME              22 (CHUNKS_CACHE_PATH)

 42           LOAD_NAME               10 (PROCESSED_DIR)
              LOAD_CONST              20 ('pageindex_doc_ids.json')
              BINARY_OP               11 (/)
              STORE_NAME              23 (PAGEINDEX_DOC_IDS_PATH)

 44           LOAD_NAME                1 (os)
              LOAD_ATTR               38 (getenv)
              PUSH_NULL
              LOAD_CONST              21 ('OPENAI_API_KEY')
              LOAD_CONST              17 ('')
              CALL                     2
              STORE_NAME              24 (OPENAI_API_KEY)

 45           LOAD_NAME                1 (os)
              LOAD_ATTR               38 (getenv)
              PUSH_NULL
              LOAD_CONST              22 ('JINA_API_KEY')
              LOAD_CONST              17 ('')
              CALL                     2
              STORE_NAME              25 (JINA_API_KEY)

 46           LOAD_NAME                1 (os)
              LOAD_ATTR               38 (getenv)
              PUSH_NULL
              LOAD_CONST              23 ('PAGEINDEX_API_KEY')
              LOAD_CONST              17 ('')
              CALL                     2
              STORE_NAME              26 (PAGEINDEX_API_KEY)
              RETURN_CONST             2 (None)
